{
    "totals": {
        "morning_picking_over": 14901.300000000001,
        "total_picking_over": 15267.150000000001,
        "days": 10,
        "midday_picking_over": 365.85,
        "total_staging_over": 0,
        "late_picking_over": 0,
        "total_gate_over": 69
    },
    "summary_by_day": [
        {
            "gate_over_sum": 12,
            "pressure_mode": "picking",
            "picking_over_sum": 1764.7700000000002,
            "staging_over_sum": 0,
            "depot_penalty": 16153.24,
            "late_picking_over": 0,
            "morning_picking_over": 1760.7700000000002,
            "overload_bucket_count": 20,
            "peak_picking_bucket": "06:00",
            "date": "2026-01-01",
            "midday_picking_over": 4,
            "peak_picking_over": 310.87
        },
        {
            "gate_over_sum": 4,
            "pressure_mode": "picking",
            "picking_over_sum": 1297,
            "staging_over_sum": 0,
            "depot_penalty": 11028,
            "late_picking_over": 0,
            "morning_picking_over": 1297,
            "overload_bucket_count": 15,
            "peak_picking_bucket": "05:45",
            "date": "2026-01-02",
            "midday_picking_over": 0,
            "peak_picking_over": 163.96
        },
        {
            "gate_over_sum": 7,
            "pressure_mode": "picking",
            "picking_over_sum": 1936.5800000000002,
            "staging_over_sum": 0,
            "depot_penalty": 16824.96,
            "late_picking_over": 0,
            "morning_picking_over": 1936.5800000000002,
            "overload_bucket_count": 18,
            "peak_picking_bucket": "05:30",
            "date": "2026-01-03",
            "midday_picking_over": 0,
            "peak_picking_over": 293.46000000000004
        },
        {
            "gate_over_sum": 8,
            "pressure_mode": "picking",
            "picking_over_sum": 2065.46,
            "staging_over_sum": 0,
            "depot_penalty": 18209.52,
            "late_picking_over": 0,
            "morning_picking_over": 2023.46,
            "overload_bucket_count": 22,
            "peak_picking_bucket": "05:45",
            "date": "2026-01-04",
            "midday_picking_over": 42,
            "peak_picking_over": 277.45
        },
        {
            "gate_over_sum": 8,
            "pressure_mode": "picking",
            "picking_over_sum": 2355.4100000000003,
            "staging_over_sum": 0,
            "depot_penalty": 20564.920000000002,
            "late_picking_over": 0,
            "morning_picking_over": 2308.4100000000003,
            "overload_bucket_count": 20,
            "peak_picking_bucket": "05:00",
            "date": "2026-01-05",
            "midday_picking_over": 47,
            "peak_picking_over": 237.14
        },
        {
            "gate_over_sum": 8,
            "pressure_mode": "picking",
            "picking_over_sum": 2027.56,
            "staging_over_sum": 0,
            "depot_penalty": 17698.72,
            "late_picking_over": 0,
            "morning_picking_over": 1781.71,
            "overload_bucket_count": 24,
            "peak_picking_bucket": "06:00",
            "date": "2026-01-06",
            "midday_picking_over": 245.85,
            "peak_picking_over": 258.51
        },
        {
            "gate_over_sum": 16,
            "pressure_mode": "picking",
            "picking_over_sum": 2623.22,
            "staging_over_sum": 0,
            "depot_penalty": 24102.64,
            "late_picking_over": 0,
            "morning_picking_over": 2596.22,
            "overload_bucket_count": 22,
            "peak_picking_bucket": "06:00",
            "date": "2026-01-07",
            "midday_picking_over": 27,
            "peak_picking_over": 596.8199999999999
        },
        {
            "gate_over_sum": 6,
            "pressure_mode": "picking",
            "picking_over_sum": 933.37,
            "staging_over_sum": 0,
            "depot_penalty": 8700.44,
            "late_picking_over": 0,
            "morning_picking_over": 933.37,
            "overload_bucket_count": 7,
            "peak_picking_bucket": "05:15",
            "date": "2026-01-08",
            "midday_picking_over": 0,
            "peak_picking_over": 200.26
        },
        {
            "gate_over_sum": 0,
            "pressure_mode": "picking",
            "picking_over_sum": 88,
            "staging_over_sum": 0,
            "depot_penalty": 704,
            "late_picking_over": 0,
            "morning_picking_over": 88,
            "overload_bucket_count": 5,
            "peak_picking_bucket": "05:45",
            "date": "2026-01-09",
            "midday_picking_over": 0,
            "peak_picking_over": 27
        },
        {
            "gate_over_sum": 0,
            "pressure_mode": "picking",
            "picking_over_sum": 175.78,
            "staging_over_sum": 0,
            "depot_penalty": 1449.3600000000001,
            "late_picking_over": 0,
            "morning_picking_over": 175.78,
            "overload_bucket_count": 6,
            "peak_picking_bucket": "05:45",
            "date": "2026-01-10",
            "midday_picking_over": 0,
            "peak_picking_over": 83.84
        }
    ]
}